{"top_header_time": "1966年8月8日09-11時", "top_table_header": [["8月", "8"], ["己亥日 ", "巳時", "( 09-11時 )"]], "get_top_table": [[["8月", "8"], ["己亥日 ", "巳時", "( 09-11時 )"]], [["1966年8月8日09-11時", [["〔年〕", "〔月〕", "〔日〕", "〔時〕"], ["丙午", "六", "廿二", "巳"], ["正印", "正印", "(命主)", "比肩"], [["丙", "火"], ["丙", "火"], ["己", "土"], ["己", "土"]], [["午", "火"], ["申", "金"], ["亥", "水"], ["巳", "火"]], [["偏印", "比肩"], ["傷官", "劫財", "正財"], ["正財", "正官"], ["正印", "傷官", "劫財"]]], ["", " ", ""]], [["【農曆】", "丙午年六月廿二日巳時"], ["【生肖】", "馬", ["【命重】", "5兩4錢"]], ["【命主】", "己土", ["【命格】", "傷官格"]], ["【五行】", "金(1),木(0),水(1),火(4),土(2)"], ["【空亡】", "辰巳寅卯 (時柱帶空亡) "], "貴造為陽男，出生後10 年 4 個月又 0 天交大運", [["歲", "11", "21", "31", "41", "51", "61", "71", "81"], [["大", "運"], "丁酉", "戊戌", "己亥", "庚子", "辛丑", "壬寅", "癸卯", "甲辰"]]]]], "get_panel_head_nav": ["五行結構", "命盤分析", "大運吉凶", "流年運勢", "趨吉避凶", "秤骨論命", "生肖論命"], "get_panel1": [[["原局五行結構", "合會生剋後五行結構"], ["木 (官殺)", [" ", "5%"], [" ", "5%"]], ["火 (印星)", [" ", "36%"], [" ", "37%"]], ["命主★", "土 (比劫)", [" ", "29%"], [" ", "30%"]], ["金 (食傷)", [" ", "15%"], [" ", "14%"]], ["水 (財星)", [" ", "14%"], [" ", "13%"]]], [["【會合成化說明】", "地支巳申合，時值申月為水長生之地，但水勢偏弱與土對恃，巳申合水不能成化。"], ["【干支生剋說明】", "月柱丙申，干克支，丙火申金皆減力，受剋損傷較大。日干己土自坐亥水，干克支，干支皆減力，受剋損傷較大。時柱己巳，支生干，干加力支減力。年柱丙午，干支比和一氣，干支皆增力。地支巳亥緊貼相沖。"], ["【日主強弱說明】", "己生申月，土休失令，但局中幫扶略多，日主身強。"]]], "get_panel2": ["◎八字特點", "己生申月，土休失令，但局中幫扶略多，日主身強。局成", "傷官格", "，以", "財星", "為用神，喜", "食傷", "，忌", "比劫 印星", "，行運喜", "水金", "運，忌", "土火", "運。", [[["【命造格局說明】", "己生申月，干上未透月支，取傷官為格。"], ["【用神喜忌說明】", "日主強，比劫眾，印綬多，生身太過，取財星破印使日主中和為用神。"]], "◎性格分析", "性格方面，日干己土，主多才多藝，但善變不定。局中以正財為用，主保守安分，勤儉節約，重視生活保障。比肩為忌，主乖僻寡和，行事剛愎自用，要面子，氣量狹小，易與人發生爭執。", [["【命主註釋】", "己土屬陰，象徵田園之土，命主多才多藝，肯接納，有涵養，理解能力強。欠缺專注，易消極妥協。"], "◎命盤分析", "原局為中等命。局中用神有情但力量中和，虛神為用而又適為真神，運逢喜用之地，則可枝葉茂盛成就富貴。但逢大運剋，再重遇歲運剋，則必有災禍之險。又用神被緊貼剋傷，主力量不易發揮，行事多挫折或常受拖累。", ["【用神高低說明】", ["．命盤所取用神，恰為日主最需要之物，故用神有情。", "．時值申月水相得令，用神力量中和。", "．用神親近日主，用神團結。", "．命盤通關、調候用神不緊缺，只需取扶抑用神。", "．用神被忌神緊貼剋傷，濁而不清。"]]]]], "get_panel3": [["◎運程分析", "命盤所取用神有情、力量一般，用神被緊貼剋傷，主力量不易發揮，行事多挫折或常受拖累。早年運勢不佳，常有疾災，誤交損友，煩惱必接踵而至；中年得運吉多於凶，生涯境遇安泰，苦心奮鬥，可穩達成功發展；晚年吉凶互見，力求和平可獲安然而少災。"], ["人生十年大運起伏圖", ["歲", ["11-20", "丁酉"], ["21-30", "戊戌"], ["31-40", "己亥"], ["41-50", "庚子"], ["51-60", "辛丑"], ["61-70", "壬寅"], ["71-80", "癸卯"], ["81-90", "甲辰"]], ["每一色條代表十年的大運平均運氣，分為紅色(好運)、橘色(普通運)、綠色(壞運)，色條越長越好。", "紅色，代表你那十年會比較走運，要積極把握奮鬥。", "綠色，代表你那十年會比較不走運，宜保守謹慎規劃。", "十年大運只是提示此階段大致的吉凶，命造真正流年的吉凶，要視大運、流年的作用結果而定。通常壞運中必有少數流年應吉，好運中也必有少數流年應凶。具體吉凶請詳「八字流年批算」。"]], [["以下為大運吉凶的訊息判斷（行運喜", "水金", "運，忌", "土火", "運。）"], ["11 - 丁酉", "平順", ["◆丁酉運：干克支，丁火剋酉金之象。為火金運。", ["生剋：", "丁火坐酉中辛金，陰火剋辛金，力減。酉中辛金受剋，力弱。"], "◆行運吉凶", [["干運：", "八字忌火，卻逢丁酉運天干為忌神，此運欠佳。"], ["支運：", "八字喜金，逢丁酉運地支為喜神，此運吉祥。"], ["大運：", "行丁酉運半吉半凶，忌喜神勢均，此運平順。"]]]], ["21 - 戊戌", "大凶", ["◆戊戌運：戊土戌土比和一氣之象。為土專旺運。", ["生剋：", "戊土坐戌中戊土辛金丁火，厚土疊疊，旺而力強。丁火僅得雜氣，氣極弱。戌中辛金以土為印，雖僅得餘氣，氣仍不弱。"], "◆行運吉凶", [["干運：", "八字忌土，卻逢戊戌運天干為忌神，此運不吉。"], ["支運：", "八字忌土，卻逢戊戌運地支為忌神，此運不吉。"], ["大運：", "八字忌土，卻逢戊戌運忌神通根強旺，此運多災。"]]]], ["31 - 己亥", "吉多於凶", ["◆己亥運：干克支，己土剋亥水之象。為土水運。", ["生剋：", "己土坐亥中壬水甲木，剋壬水並被甲木剋傷，其力稍弱。亥中甲木僅得餘氣，氣弱。亥中壬水受剋，力減。"], "◆行運吉凶", [["干運：", "八字忌土，卻逢己亥運天干為忌神，此運不吉。"], ["支運：", "八字喜水，逢己亥運地支為喜神，此運吉利。且大運亥水沖去忌神巳火，有利命局。"], ["大運：", "行己亥運吉凶參半，喜神力量稍強。"]]]], ["41 - 庚子", "大吉", ["◆庚子運：干生支，庚金生子水之象。為金水運。", ["生剋：", "庚金坐子中癸水，生水耗力稍弱。子中癸水受生，力強。"], "◆行運吉凶", [["干運：", "八字喜金，逢庚子運天干為喜神，此運吉祥。"], ["支運：", "八字喜水，逢庚子運地支為喜神，此運吉利。且大運子水沖去忌神午火，有利命局。"], ["大運：", "行庚子運喜神強旺，此運大吉。"]]]], ["51 - 辛丑", "平順", ["◆辛丑運：支生干，丑土生辛金之象。為金土運。", ["生剋：", "辛金坐丑中己土癸水辛金，得土印生身並通暗根，強旺。丑中己土生金耗力，稍弱。丑中癸水僅得餘氣，又被土剋傷，氣弱。"], "◆行運吉凶", [["干運：", "八字喜水，大運天干又和原局構成丙辛合化水，運上增吉。"], ["支運：", "八字忌土，卻逢辛丑運地支為忌神，此運不吉。"], ["大運：", "行辛丑運半吉半凶，忌喜神勢均，此運平順。"]]]], ["61 - 壬寅", "平順", ["◆壬寅運：干生支，壬水生寅木之象。為水木運。", ["生剋：", "壬水坐寅中甲木丙火戊土，有剋耗，稍弱。寅中丙火得木生身，雖僅得餘氣，氣不弱。寅中戊土僅得雜氣，氣極弱。寅中甲木受生，力強。"], "◆行運吉凶", [["干運：", "八字喜水，逢壬寅運天干為喜神，此運吉利。"], ["支運：", "大運和原局構成寅亥合木為閒神，此運平順。大運和原局構成寅亥合木，合住喜用神亥水，不利命局。且大運寅木沖去喜用神申金，不利命局。"], ["大運：", "行壬寅運半吉半凶，忌喜神勢均，此運平順。"]]]], ["71 - 癸卯", "中吉", ["◆癸卯運：干生支，癸水生卯木之象。為水木運。", ["生剋：", "癸水坐卯中乙木，生木耗力稍弱。卯中乙木得生氣旺。"], "◆行運吉凶", [["干運：", "八字喜水，逢癸卯運天干為喜神，此運吉利。"], ["支運：", "支運為閒神。八字喜水，逢癸卯運地支無忌且暗藏喜神，此運平吉。"], ["大運：", "行癸卯運喜神力強，此運多福。"]]]], ["81 - 甲辰", "大凶", ["◆甲辰運：干克支，甲木剋辰土之象。為木土運。", ["生剋：", "甲木坐辰中戊土乙木癸水，剋土且有暗根為朋，其力強旺。辰中戊土受剋，其力稍弱。辰中癸水僅得雜氣，氣極弱。"], "◆行運吉凶", [["干運：", "八字忌土，大運天干卻和原局構成甲己合化土，忌神力量增加，運上增阻。"], ["支運：", "八字忌土，卻逢甲辰運地支為忌神，此運不吉。"], ["大運：", "行甲辰運忌神強旺，此運多災。"]]]]], ["※", "行運必有起伏，其中以中壯年得吉運最佳，少年吃苦無彷，老年宜平順。古人常言：命定一世榮枯，運言一時休咎。命好運好，可以富貴到老；命好運不好，只能懷才求溫飽；命不好運好，把握機會有福報；命不好運不好，恐怕窮苦到身老。"]], "get_panel3_columnar": [{"src": "/images/bar_base.gif", "style": "width:5px; height:130px; vertical-align: bottom; "}, {"src": "/images/bar_org.gif", "style": "width:30px; height:70px; vertical-align: bottom; "}, {"src": "/images/bar_green.gif", "style": "width:30px; height:42px; vertical-align: bottom; "}, {"src": "/images/bar_org.gif", "style": "width:30px; height:79px; vertical-align: bottom; "}, {"src": "/images/bar_red.gif", "style": "width:30px; height:110px; vertical-align: bottom; "}, {"src": "/images/bar_org.gif", "style": "width:30px; height:70px; vertical-align: bottom; "}, {"src": "/images/bar_org.gif", "style": "width:30px; height:70px; vertical-align: bottom; "}, {"src": "/images/bar_red.gif", "style": "width:30px; height:100px; vertical-align: bottom; "}, {"src": "/images/bar_green.gif", "style": "width:30px; height:42px; vertical-align: bottom; "}], "get_panel4": ["劍靈命理系統以命主「命盤八字喜忌」，配合「流年干支」，批算命造今年運勢如下：", [["  流年：", "2020，庚子鼠年"], ["  大運：", "命造今年實歲54歲，行辛丑大運。"], ["◎流年運勢分析", "就大運流年運程而言，歲逢庚子流年，大運與流年地支子丑合土，大運運勢半吉半凶，流年運程吉凶參半，主今年運勢不太順遂，可能會遭遇一些失敗與打擊，凡事要更加小心謹慎。"], " ", ["說明", "「今年運勢預測」是以命主的八字喜忌，配合大運流年，以批算出命主今年的運勢，僅作為參考。"]]], "get_panel5": ["◎開運方法", ["  行業選擇：", "命局喜水金，行業以電子業、金融業、汽車業、珠寶業、民代、大眾傳播、航海界、運輸業、旅遊業、記者、自由業等為佳。"], ["  職業性質：", "局成傷官格，適合文藝性質、活潑變化之工作。"], ["  吉利方位：", "命局喜水金，方位以西、北為吉位，就學就業宜往西、北方去求(以出生地或居住地為出發點)，較易獲得。"], ["  幸運色彩：", "命局喜水金，衣著、車輛、家中佈置顏色以白色系、黑色系等為佳。"], ["  幸運數字：", "命局喜水金，電話、車牌等號碼以四、九、一、六等較具開運效果。"], ["  身體疾病：", "命局忌土火，身體狀況宜注意心臟、腦中風、血液、眼睛、腸、胃等消化系統等疾病。"]], "get_panel6": [["◎八字命重", "  命重：5兩4錢", ["  命批：有勇有謀威權富貴財祿之命！", "  歌訣：此命推來厚且清，詩書滿腹看功成。豐衣足食自然穩，正是人間有福人。"]], ["說明", ["1. 「秤骨論命」是依袁天罡先師「八字秤命術」合算生辰八字共幾兩數，對照農民曆上常見的《秤骨歌訣》，查出一生榮枯。", "2. 秤骨論命法通俗簡易，查表即可得知命重，應驗性低，僅作為參考！。"]]], "get_panel7": ["劍靈命理系統以命主所屬「生肖」、「年命納音五行」批算命造運勢如下：", ["【陽曆】：", "1966年8月8日10時", "【農曆】：", "丙午年六月廿二日巳時", "【納音五行】：", "丙午天河水", [["水馬", [["丙午年生，五行屬水，為【行路之馬】。為人清閒，初年財帛耗散，心主不憂不住，宜做手藝工夫生意，不利求名，兄弟各自成家，後運發財興旺，女人清奇巧妙之命。", "屬馬的人，生於六月，粗茶淡飯，衣食欠佳，終身勞碌。干戈不止，疫病牽纏，諸事不順。"], "《三命通會》論丙午天河水：銀漢之水，土不能剋，天上之水，地金不能生也，生旺太過，反傷於萬物，死絕太多，又不能生萬物，《五行要論》云：「丙午，至崇之水，體南方溫厚之氣。稟之者類有道氣虛變，穎異有為，魁眾出倫。」"]], ["說明", "「生肖論命」是以命主的八字「年柱」，依六十甲子納音取出年命五行，再取地支對應所屬生肖，以生肖五行屬相來瞭解命運，僅作為參考。"]]]], "zodiac": "/images/12/D07.gif"}